saritasa_invocations/__init__.py
saritasa_invocations/_config.py
saritasa_invocations/alembic.py
saritasa_invocations/celery.py
saritasa_invocations/cruft.py
saritasa_invocations/db.py
saritasa_invocations/db_k8s.py
saritasa_invocations/django.py
saritasa_invocations/docker.py
saritasa_invocations/fastapi.py
saritasa_invocations/git.py
saritasa_invocations/github_actions.py
saritasa_invocations/k8s.py
saritasa_invocations/mypy.py
saritasa_invocations/open_api.py
saritasa_invocations/pip.py
saritasa_invocations/poetry.py
saritasa_invocations/pre_commit.py
saritasa_invocations/printing.py
saritasa_invocations/py.typed
saritasa_invocations/pytest.py
saritasa_invocations/python.py
saritasa_invocations/secrets.py
saritasa_invocations/system.py
saritasa_invocations/uv.py
saritasa_invocations-1.9.1.dist-info/METADATA
saritasa_invocations-1.9.1.dist-info/WHEEL
saritasa_invocations-1.9.1.dist-info/entry_points.txt
saritasa_invocations-1.9.1.dist-info/licenses/LICENSE
saritasa_invocations-1.9.1.dist-info/RECORD
