Metadata-Version: 2.4
Name: saritasa-invocations
Version: 1.9.1
Summary: Collection of invoke commands used by Saritasa
License: MIT
License-File: LICENSE
Keywords: python,invoke
Author: Saritasa
Author-email: pypi@saritasa.com
Maintainer: Stanislav Khlud
Maintainer-email: stanislav.khlud@saritasa.com
Requires-Python: >=3.10
Classifier: Development Status :: 5 - Production/Stable
Classifier: Environment :: Console
Classifier: Intended Audience :: Developers
Classifier: License :: OSI Approved :: MIT License
Classifier: Natural Language :: English
Classifier: Operating System :: OS Independent
Classifier: Programming Language :: Python :: 3
Classifier: Programming Language :: Python :: 3.10
Classifier: Programming Language :: Python :: 3.11
Classifier: Programming Language :: Python :: 3.12
Classifier: Programming Language :: Python :: 3.13
Classifier: Programming Language :: Python :: 3.14
Classifier: Topic :: Software Development :: Libraries :: Python Modules
Provides-Extra: env-settings
Requires-Dist: invoke (>=2,<3)
Requires-Dist: python-decouple (>=3,<4) ; extra == "env-settings"
Requires-Dist: rich (>=13,<15)
Project-URL: Homepage, https://pypi.org/project/saritasa-invocations/
Project-URL: Repository, https://github.com/saritasa-nest/saritasa-invocations/
